pyzctrl/__init__.py
pyzctrl/utils.py
pyzctrl/devices/__init__.py
pyzctrl/devices/aquanot.py
pyzctrl/devices/basic.py
pyzctrl/devices/battery.py
pyzctrl/devices/connection.py
pyzctrl/devices/float.py
pyzctrl/devices/pump.py
pyzctrl-0.3.0.dist-info/METADATA
pyzctrl-0.3.0.dist-info/WHEEL
pyzctrl-0.3.0.dist-info/licenses/LICENSE
pyzctrl-0.3.0.dist-info/RECORD
