Metadata-Version: 2.1
Name: pyzctrl
Version: 0.3.0
Summary: Simple API to interact with select ZControl® devices.
Project-URL: Homepage, https://github.com/soaresbrun0/pyzctrl
Project-URL: Issues, https://github.com/soaresbrun0/pyzctrl/issues
Author-email: Bruno Soares <soaresbruno@gmail.com>
License: MIT License
License-File: LICENSE
Keywords: zcontrol,zoeller
Classifier: License :: OSI Approved :: MIT License
Classifier: Operating System :: OS Independent
Classifier: Programming Language :: Python :: 3
Requires-Python: >=3.9.2
Requires-Dist: requests
Requires-Dist: xmltodict
